python_module_loader/__init__.py
python_module_loader/helpers.py
python_module_loader/loader.py
python_module_loader/models.py
tests/__init__.py
tests/test_helpers.py
tests/test_loader.py
tests/test_models.py
tests/test_package.py
tests/example/__init__.py
tests/example/module1.py
tests/example/module2.py
tests/example/submodule/__init__.py
tests/example/submodule/submodule1.py
tests/example/submodule/submodule2.py
python_module_loader-0.1.1.dist-info/METADATA
python_module_loader-0.1.1.dist-info/WHEEL
python_module_loader-0.1.1.dist-info/top_level.txt
python_module_loader-0.1.1.dist-info/RECORD
