Metadata-Version: 2.1
Name: python-module-loader
Version: 0.1.1
Summary: Python package for auto-loading modules and their objects.
Home-page: https://github.com/Sinma1/python-module-loader
Author: Damian Ciftci
License: MIT
Platform: UNKNOWN
Classifier: Programming Language :: Python
Classifier: Programming Language :: Python :: 3
Classifier: License :: OSI Approved :: MIT License
Classifier: Operating System :: OS Independent
Classifier: Intended Audience :: Developers
Classifier: Topic :: Software Development :: Libraries :: Python Modules
